Metadata-Version: 1.1
Name: hops-ipython-sql
Version: 0.3.9
Summary: RDBMS access via IPython
Home-page: https://github.com/logicalclocks/ipython-sql
Author: Catherine Devlin, Fabio Buso
Author-email: catherine.devlin@gmail.com, fabio@logicalclocks.com
License: MIT
Keywords: database ipython postgresql mysql
Platform: UNKNOWN
Classifier: Development Status :: 3 - Alpha
Classifier: Environment :: Console
Classifier: License :: OSI Approved :: MIT License
Classifier: Topic :: Database
Classifier: Topic :: Database :: Front-Ends
Classifier: Programming Language :: Python :: 3
Classifier: Programming Language :: Python :: 2
